py_benchmark_functions/__init__.py
py_benchmark_functions/config/__init__.py
py_benchmark_functions/core/__init__.py
py_benchmark_functions/core/function.py
py_benchmark_functions/core/metadata.py
py_benchmark_functions/core/transformation.py
py_benchmark_functions/factory/__init__.py
py_benchmark_functions/factory/builder.py
py_benchmark_functions/factory/registry.py
py_benchmark_functions/imp/__init__.py
py_benchmark_functions/imp/numpy.py
py_benchmark_functions/imp/tensorflow.py
py_benchmark_functions/imp/torch.py
py_benchmark_functions/info/__init__.py
py_benchmark_functions/plot/__init__.py
py_benchmark_functions/plot/drawer.py
py_benchmark_functions-0.2.3.dist-info/METADATA
py_benchmark_functions-0.2.3.dist-info/WHEEL
py_benchmark_functions-0.2.3.dist-info/top_level.txt
py_benchmark_functions-0.2.3.dist-info/RECORD
