Metadata-Version: 2.4
Name: py_benchmark_functions
Version: 0.2.3
Summary:  Python benchmark functions for Optimization with NumPy, TensorFlow and PyTorch support.
Author: Gabriel Barbosa
Author-email: Moésio Filho <moesio.f@gmail.com>
Maintainer-email: Moésio Filho <moesio.f@gmail.com>
Project-URL: repository, https://github.com/moesio-f/py-benchmark-functions
Keywords: optimization,benchmark,numpy,tensorflow,torch,benchmark functions,global optimization
Classifier: Development Status :: 4 - Beta
Classifier: Programming Language :: Python :: 3.8
Classifier: Programming Language :: Python :: 3.9
Classifier: Programming Language :: Python :: 3.10
Classifier: Programming Language :: Python :: 3.11
Classifier: Programming Language :: Python :: 3.12
Requires-Python: >=3.8
Requires-Dist: numpy>=1.21.0
Requires-Dist: matplotlib>=3.0.0
Provides-Extra: dev
Requires-Dist: pytest; extra == "dev"
Requires-Dist: pytest-timeout; extra == "dev"
Provides-Extra: tensorflow
Requires-Dist: tensorflow>=2.0.0; extra == "tensorflow"
Provides-Extra: torch
Requires-Dist: torch>=2.0.0; extra == "torch"
